ene/__init__.py
ene/__main__.py
ene/cli.py
ene-0.1.1.dist-info/entry_points.txt
ene-0.1.1.dist-info/LICENSE
ene-0.1.1.dist-info/WHEEL
ene-0.1.1.dist-info/METADATA
ene-0.1.1.dist-info/RECORD
