Metadata-Version: 2.1
Name: ene
Version: 0.1.1
Summary: Automatically track and sync anime watching progress
Home-page: https://github.com/MaT1g3R/ene
License: GPL-3.0+
Author: Peijun Ma
Author-email: peijun.ma@protonmail.com
Requires-Python: >=3.6
Classifier: Development Status :: 1 - Planning
Classifier: License :: OSI Approved :: GNU General Public License v3 or later (GPLv3+)
Classifier: Programming Language :: Python :: 3
Classifier: Programming Language :: Python :: 3.6
Classifier: Programming Language :: Python :: 3.7
Requires-Dist: attrs (>=18)
Requires-Dist: click (>=6)
